{
  "id": "system-shortcuts",
  "name": "Keyboard Shortcuts",
  "description": "Define custom keyboard shortcuts per-site. Navigate, click, scroll, toggle visibility, or run JS snippets. Press Alt+K to open the shortcuts panel.",
  "author": "domo",
  "version": "1.0.0",
  "tags": ["system", "shortcuts", "utility", "keyboard"],
  "platform": "system",
  "match": { "type": "site", "host": "*" },
  "defaultPriority": 15,
  "options": {},
  "code": {
    "css": "",
    "html": "",
    "js": "var hostname = location.hostname;\nvar STORAGE_KEY = 'domo_shortcuts_' + hostname;\nvar PANEL_ID = '__domo_shortcuts_panel__';\nvar TOGGLE_STYLE_ID = '__domo_toggle_style__';\n\n// ── State ──\nvar shortcuts = [];\ntry { shortcuts = JSON.parse(localStorage.getItem(STORAGE_KEY) || '[]'); } catch(e) { shortcuts = []; }\nvar panelOpen = false;\nvar panelHost = null;\nvar panelShadow = null;\nvar editing = null; // null or shortcut id\nvar recording = false;\nvar recordedCombo = '';\n\nvar BUILTIN = [\n  { shortcut: 'Alt+H', label: 'Toggle hide mode', builtin: true },\n  { shortcut: 'Alt+K', label: 'Toggle shortcuts panel', builtin: true }\n];\n\n// ── Persistence ──\nfunction save() {\n  localStorage.setItem(STORAGE_KEY, JSON.stringify(shortcuts));\n}\n\nfunction genId() {\n  var b = new Uint8Array(4);\n  crypto.getRandomValues(b);\n  return 's_' + Array.from(b, function(x) { return x.toString(16).padStart(2, '0'); }).join('');\n}\n\n// ── Key Normalization ──\nfunction normalizeEvent(e) {\n  var parts = [];\n  if (e.ctrlKey) parts.push('Ctrl');\n  if (e.altKey) parts.push('Alt');\n  if (e.shiftKey) parts.push('Shift');\n  if (e.metaKey) parts.push('Meta');\n  var key = e.key;\n  if (!key) return '';\n  if (key === ' ') key = 'Space';\n  if (key.length === 1) key = key.toUpperCase();\n  if (['Control', 'Alt', 'Shift', 'Meta'].indexOf(key) === -1) parts.push(key);\n  return parts.join('+');\n}\n\nfunction hasModifier(combo) {\n  return combo.indexOf('Ctrl+') !== -1 || combo.indexOf('Alt+') !== -1 || combo.indexOf('Shift+') !== -1 || combo.indexOf('Meta+') !== -1;\n}\n\nfunction isTextInput(el) {\n  if (!el) return false;\n  var tag = el.tagName;\n  if (tag === 'INPUT' || tag === 'TEXTAREA' || tag === 'SELECT') return true;\n  if (el.isContentEditable) return true;\n  return false;\n}\n\n// ── Action Executors ──\nfunction exec(s) {\n  try {\n    if (s.action === 'navigate') {\n      var url = s.config.url || '';\n      if (url.startsWith('/') || url.startsWith('#')) url = location.origin + url;\n      location.href = url;\n    } else if (s.action === 'click') {\n      var el = document.querySelector(s.config.selector);\n      if (el) el.click();\n    } else if (s.action === 'scroll') {\n      if (s.config.selector) {\n        var el = document.querySelector(s.config.selector);\n        if (el) el.scrollIntoView({ behavior: 'smooth', block: 'center' });\n      } else if (s.config.position === 'bottom') {\n        window.scrollTo({ top: document.body.scrollHeight, behavior: 'smooth' });\n      } else {\n        window.scrollTo({ top: 0, behavior: 'smooth' });\n      }\n    } else if (s.action === 'toggle') {\n      var el = document.querySelector(s.config.selector);\n      if (el) {\n        var hidden = el.getAttribute('data-domo-hidden');\n        if (hidden) {\n          el.removeAttribute('data-domo-hidden');\n          el.style.removeProperty('display');\n        } else {\n          el.setAttribute('data-domo-hidden', '1');\n          el.style.setProperty('display', 'none', 'important');\n        }\n      }\n    } else if (s.action === 'js') {\n      new Function(s.config.code)();\n    }\n  } catch (err) {\n    console.warn('[domo shortcuts] action failed:', err);\n  }\n}\n\n// ── Keyboard Listener ──\napi.addEventListener(window, 'keydown', function(e) {\n  try {\n    if (isTextInput(document.activeElement)) return;\n    var combo = normalizeEvent(e);\n    if (!combo || !hasModifier(combo)) return;\n    for (var i = 0; i < shortcuts.length; i++) {\n      if (shortcuts[i].shortcut === combo) {\n        e.preventDefault();\n        e.stopPropagation();\n        exec(shortcuts[i]);\n        return;\n      }\n    }\n  } catch(err) {}\n}, { capture: true });\n\n// ── Element Picker (inlined) ──\nfunction computeSelector(el) {\n  if (!(el instanceof Element)) return null;\n  if (el.id && !el.id.startsWith('__domo')) return '#' + CSS.escape(el.id);\n  var testId = el.getAttribute('data-testid') || el.getAttribute('data-test-id');\n  if (testId) return '[data-testid=\"' + testId.replace(/\"/g, '\\\\\"') + '\"]';\n  var parts = [];\n  var cur = el;\n  for (var i = 0; i < 6 && cur && cur.nodeType === 1 && cur !== document.body; i++) {\n    var tag = cur.tagName.toLowerCase();\n    if (!tag) break;\n    var parent = cur.parentElement;\n    if (!parent) { parts.unshift(tag); break; }\n    var siblings = Array.from(parent.children).filter(function(c) { return c.tagName === cur.tagName; });\n    var idx = siblings.indexOf(cur) + 1;\n    var piece = siblings.length > 1 ? tag + ':nth-of-type(' + idx + ')' : tag;\n    parts.unshift(piece);\n    if (parent.id && !parent.id.startsWith('__domo')) {\n      parts.unshift('#' + CSS.escape(parent.id));\n      break;\n    }\n    cur = parent;\n  }\n  return parts.join(' > ');\n}\n\nfunction pickElement() {\n  return new Promise(function(resolve) {\n    var active = true;\n    var overlay = document.createElement('div');\n    overlay.style.cssText = 'position:fixed;inset:0;z-index:2147483646;cursor:crosshair;background:rgba(0,0,0,0.02);pointer-events:none;';\n    var highlight = document.createElement('div');\n    highlight.style.cssText = 'position:fixed;z-index:2147483647;pointer-events:none;border:2px solid #58a6ff;border-radius:6px;box-shadow:0 0 0 4px rgba(88,166,255,.15);';\n    function isOurUI(el) {\n      while (el) {\n        if (el.id && (el.id.startsWith('__domo') || el.getAttribute && el.getAttribute('data-domo'))) return true;\n        el = el.parentElement;\n      }\n      return false;\n    }\n    function cleanup() {\n      active = false; overlay.remove(); highlight.remove();\n      document.documentElement.style.cursor = '';\n      window.removeEventListener('keydown', onKey, true);\n      document.removeEventListener('mousemove', onMove, true);\n      document.removeEventListener('click', onClick, true);\n    }\n    function onKey(e) { if (e.key === 'Escape') { e.preventDefault(); e.stopPropagation(); cleanup(); resolve(null); } }\n    function onMove(e) {\n      if (!active) return;\n      var el = document.elementFromPoint(e.clientX, e.clientY);\n      if (!el || isOurUI(el)) return;\n      var r = el.getBoundingClientRect();\n      highlight.style.left = Math.max(0, r.left) + 'px'; highlight.style.top = Math.max(0, r.top) + 'px';\n      highlight.style.width = Math.max(0, r.width) + 'px'; highlight.style.height = Math.max(0, r.height) + 'px';\n    }\n    function onClick(e) {\n      if (!active) return; e.preventDefault(); e.stopPropagation();\n      var el = document.elementFromPoint(e.clientX, e.clientY);\n      if (!el || isOurUI(el)) return; cleanup(); resolve(el);\n    }\n    document.body.appendChild(overlay); document.body.appendChild(highlight);\n    document.documentElement.style.cursor = 'crosshair';\n    window.addEventListener('keydown', onKey, true);\n    document.addEventListener('mousemove', onMove, true);\n    document.addEventListener('click', onClick, true);\n  });\n}\n\n// ── Floating Panel ──\nfunction esc(s) { return String(s).replace(/&/g,'&amp;').replace(/</g,'&lt;').replace(/>/g,'&gt;').replace(/\"/g,'&quot;'); }\n\nfunction openPanel() {\n  if (panelHost) closePanel();\n  panelOpen = true; editing = null;\n  panelHost = document.createElement('div');\n  panelHost.id = PANEL_ID;\n  panelHost.style.cssText = 'all:initial;position:fixed;bottom:16px;right:16px;z-index:2147483645;';\n  panelShadow = panelHost.attachShadow({ mode: 'closed' });\n  renderList();\n  document.body.appendChild(panelHost);\n  api.addEventListener(document, 'keydown', function(e) {\n    if (e.key === 'Escape' && panelOpen && !recording) { e.stopPropagation(); closePanel(); }\n  });\n}\n\nfunction closePanel() {\n  panelOpen = false; editing = null; recording = false;\n  if (panelHost) { panelHost.remove(); panelHost = null; panelShadow = null; }\n}\n\nfunction actionLabel(s) {\n  if (s.action === 'navigate') return 'navigate';\n  if (s.action === 'click') return 'click';\n  if (s.action === 'scroll') return 'scroll';\n  if (s.action === 'toggle') return 'toggle';\n  if (s.action === 'js') return 'js';\n  return s.action || '?';\n}\n\nfunction autoLabel(action, config) {\n  if (action === 'navigate') return 'Navigate to ' + (config.url || '/');\n  if (action === 'click') return 'Click ' + (config.selector || '?');\n  if (action === 'scroll') return config.selector ? 'Scroll to ' + config.selector : 'Scroll to ' + (config.position || 'top');\n  if (action === 'toggle') return 'Toggle ' + (config.selector || '?');\n  if (action === 'js') return 'Run custom JS';\n  return 'Shortcut';\n}\n\nfunction renderList() {\n  if (!panelShadow) return;\n  var items = '';\n  // Built-in\n  items += '<div class=\"section-label\">Built-in</div>';\n  BUILTIN.forEach(function(b) {\n    items += '<div class=\"item item-dim\"><div class=\"info\"><span class=\"lbl\">' + esc(b.label) + '</span></div><code>' + esc(b.shortcut) + '</code></div>';\n  });\n  // Custom\n  items += '<div class=\"section-label\" style=\"margin-top:10px\">Custom' + (shortcuts.length > 0 ? ' (' + shortcuts.length + ')' : '') + '</div>';\n  items += '<button class=\"btn bp\" id=\"add-btn\">+ Add Shortcut</button>';\n  if (shortcuts.length === 0) {\n    items += '<div class=\"empty\">No custom shortcuts on ' + esc(hostname) + '.</div>';\n  } else {\n    items += '<div class=\"list\">';\n    shortcuts.forEach(function(s, i) {\n      items += '<div class=\"item\"><div class=\"info\"><span class=\"lbl\">' + esc(s.label || autoLabel(s.action, s.config)) + '</span>' +\n        '<span class=\"tag\">' + esc(actionLabel(s)) + '</span></div>' +\n        '<code>' + esc(s.shortcut) + '</code>' +\n        '<button class=\"btn bs edit-btn\" data-i=\"' + i + '\">Edit</button>' +\n        '<button class=\"btn bs bd del-btn\" data-i=\"' + i + '\">&times;</button></div>';\n    });\n    items += '</div>';\n    items += '<button class=\"btn bd bs\" id=\"reset-btn\" style=\"margin-top:8px\">Reset All</button>';\n  }\n  panelShadow.innerHTML = '<style>' + panelCSS() + '</style>' +\n    '<div class=\"panel\"><div class=\"hdr\"><span class=\"title\">Keyboard Shortcuts</span><span class=\"sub\">' + esc(hostname) + '</span>' +\n    '<button class=\"x\" id=\"close\">&times;</button></div><div class=\"body\">' + items + '</div></div>';\n  // Wire\n  panelShadow.getElementById('close').onclick = closePanel;\n  panelShadow.getElementById('add-btn').onclick = function() { editing = null; renderForm(); };\n  var rb = panelShadow.getElementById('reset-btn');\n  if (rb) rb.onclick = function() { shortcuts = []; save(); renderList(); };\n  panelShadow.querySelectorAll('.edit-btn').forEach(function(btn) {\n    btn.onclick = function() { editing = shortcuts[parseInt(btn.dataset.i)].id; renderForm(); };\n  });\n  panelShadow.querySelectorAll('.del-btn').forEach(function(btn) {\n    btn.onclick = function() { shortcuts.splice(parseInt(btn.dataset.i), 1); save(); renderList(); };\n  });\n}\n\nfunction renderForm() {\n  if (!panelShadow) return;\n  var existing = null;\n  if (editing) existing = shortcuts.find(function(s) { return s.id === editing; });\n  var action = existing ? existing.action : 'navigate';\n  var config = existing ? existing.config : {};\n  recordedCombo = existing ? existing.shortcut : '';\n  var label = existing ? (existing.label || '') : '';\n  var title = existing ? 'Edit Shortcut' : 'New Shortcut';\n\n  function configFields(act, cfg) {\n    if (act === 'navigate') return '<label class=\"fl\">URL (relative or absolute)</label><input id=\"cfg-url\" class=\"fi\" value=\"' + esc(cfg.url || '') + '\" placeholder=\"/dashboard\">';\n    if (act === 'click') return '<label class=\"fl\">CSS Selector</label><div class=\"row\"><input id=\"cfg-sel\" class=\"fi\" style=\"flex:1\" value=\"' + esc(cfg.selector || '') + '\" placeholder=\".btn-primary\"><button class=\"btn bs\" id=\"pick-btn\">Pick</button></div>';\n    if (act === 'scroll') return '<label class=\"fl\">Scroll to</label><select id=\"cfg-pos\" class=\"fi\"><option value=\"top\"' + (cfg.position !== 'bottom' && !cfg.selector ? ' selected' : '') + '>Top</option><option value=\"bottom\"' + (cfg.position === 'bottom' ? ' selected' : '') + '>Bottom</option><option value=\"element\"' + (cfg.selector ? ' selected' : '') + '>Element</option></select>' + (cfg.selector ? '<input id=\"cfg-sel\" class=\"fi\" value=\"' + esc(cfg.selector || '') + '\" placeholder=\"#comments\" style=\"margin-top:4px\">' : '<div id=\"scroll-sel-wrap\"></div>');\n    if (act === 'toggle') return '<label class=\"fl\">CSS Selector</label><div class=\"row\"><input id=\"cfg-sel\" class=\"fi\" style=\"flex:1\" value=\"' + esc(cfg.selector || '') + '\" placeholder=\".sidebar\"><button class=\"btn bs\" id=\"pick-btn\">Pick</button></div>';\n    if (act === 'js') return '<label class=\"fl\">JavaScript code</label><textarea id=\"cfg-code\" class=\"fi ta\" rows=\"3\" placeholder=\"document.body.classList.toggle(&apos;dark&apos;)\">' + esc(cfg.code || '') + '</textarea>';\n    return '';\n  }\n\n  var actions = ['navigate', 'click', 'scroll', 'toggle', 'js'];\n  var actionLabels = { navigate: 'Navigate to URL', click: 'Click element', scroll: 'Scroll to position', toggle: 'Toggle visibility', js: 'Run JS snippet' };\n  var radios = actions.map(function(a) {\n    return '<label class=\"rl\"><input type=\"radio\" name=\"action\" value=\"' + a + '\"' + (a === action ? ' checked' : '') + '> ' + actionLabels[a] + '</label>';\n  }).join('');\n\n  panelShadow.innerHTML = '<style>' + panelCSS() + '</style>' +\n    '<div class=\"panel\"><div class=\"hdr\"><span class=\"title\">' + esc(title) + '</span>' +\n    '<button class=\"x\" id=\"cancel\">Cancel</button></div><div class=\"body\">' +\n    '<label class=\"fl\">Key combination</label>' +\n    '<div class=\"rec\" id=\"recorder\" tabindex=\"0\">' + (recordedCombo ? '<code>' + esc(recordedCombo) + '</code>' : '<span class=\"placeholder\">Click here, then press keys...</span>') + '</div>' +\n    '<div id=\"combo-err\" class=\"err\"></div>' +\n    '<label class=\"fl\" style=\"margin-top:10px\">Action</label>' +\n    '<div class=\"radios\">' + radios + '</div>' +\n    '<div id=\"config-area\">' + configFields(action, config) + '</div>' +\n    '<label class=\"fl\" style=\"margin-top:10px\">Label (optional)</label>' +\n    '<input id=\"label-input\" class=\"fi\" value=\"' + esc(label) + '\" placeholder=\"Auto-generated if empty\">' +\n    '<button class=\"btn bp\" id=\"save-btn\" style=\"margin-top:12px\">' + (existing ? 'Save Changes' : 'Add Shortcut') + '</button>' +\n    (existing ? '<button class=\"btn bd bs\" id=\"form-del\" style=\"margin-top:6px;width:100%\">Delete this shortcut</button>' : '') +\n    '</div></div>';\n\n  // Wire cancel\n  panelShadow.getElementById('cancel').onclick = function() { editing = null; recording = false; renderList(); };\n\n  // Wire recorder\n  var recEl = panelShadow.getElementById('recorder');\n  var errEl = panelShadow.getElementById('combo-err');\n  recEl.onclick = function() {\n    recording = true;\n    recEl.innerHTML = '<span class=\"placeholder\">Press a key combination...</span>';\n    errEl.textContent = '';\n    recEl.focus();\n  };\n  recEl.addEventListener('keydown', function(e) {\n    if (!recording) return;\n    e.preventDefault(); e.stopPropagation();\n    var combo = normalizeEvent(e);\n    if (!combo || ['Ctrl', 'Alt', 'Shift', 'Meta'].indexOf(e.key) !== -1) return;\n    recording = false;\n    recordedCombo = combo;\n    recEl.innerHTML = '<code>' + esc(combo) + '</code>';\n    if (!hasModifier(combo)) {\n      errEl.textContent = 'Must include a modifier (Ctrl, Alt, Shift, or Meta)';\n      recordedCombo = '';\n    } else {\n      var dup = shortcuts.find(function(s) { return s.shortcut === combo && s.id !== editing; });\n      if (dup) errEl.textContent = 'Already used: ' + (dup.label || autoLabel(dup.action, dup.config));\n      else errEl.textContent = '';\n    }\n  });\n\n  // Wire action radios\n  panelShadow.querySelectorAll('input[name=\"action\"]').forEach(function(radio) {\n    radio.onchange = function() {\n      action = radio.value;\n      config = {};\n      panelShadow.getElementById('config-area').innerHTML = configFields(action, config);\n      wireConfigExtras();\n    };\n  });\n\n  // Wire scroll position change\n  function wireConfigExtras() {\n    var posEl = panelShadow.getElementById('cfg-pos');\n    if (posEl) {\n      posEl.onchange = function() {\n        var wrap = panelShadow.getElementById('scroll-sel-wrap');\n        if (posEl.value === 'element' && wrap) {\n          wrap.innerHTML = '<input id=\"cfg-sel\" class=\"fi\" placeholder=\"#comments\" style=\"margin-top:4px\">';\n        } else if (wrap) {\n          wrap.innerHTML = '';\n        }\n      };\n    }\n    var pickBtn = panelShadow.getElementById('pick-btn');\n    if (pickBtn) {\n      pickBtn.onclick = async function() {\n        var el = await pickElement();\n        if (el) {\n          var sel = computeSelector(el);\n          var inp = panelShadow.getElementById('cfg-sel');\n          if (inp && sel) inp.value = sel;\n        }\n      };\n    }\n  }\n  wireConfigExtras();\n\n  // Wire save\n  panelShadow.getElementById('save-btn').onclick = function() {\n    if (!recordedCombo) { errEl.textContent = 'Record a key combination first'; return; }\n    if (!hasModifier(recordedCombo)) { errEl.textContent = 'Must include a modifier key'; return; }\n    var dup = shortcuts.find(function(s) { return s.shortcut === recordedCombo && s.id !== editing; });\n    if (dup) { errEl.textContent = 'Already used by another shortcut'; return; }\n    var builtinDup = BUILTIN.find(function(b) { return b.shortcut === recordedCombo; });\n    if (builtinDup) { errEl.textContent = 'Conflicts with built-in: ' + builtinDup.label; return; }\n    // Collect config\n    var cfg = {};\n    if (action === 'navigate') { cfg.url = (panelShadow.getElementById('cfg-url') || {}).value || ''; if (!cfg.url) return; }\n    if (action === 'click' || action === 'toggle') { cfg.selector = (panelShadow.getElementById('cfg-sel') || {}).value || ''; if (!cfg.selector) return; }\n    if (action === 'scroll') {\n      var posEl = panelShadow.getElementById('cfg-pos');\n      if (posEl && posEl.value === 'element') { cfg.selector = (panelShadow.getElementById('cfg-sel') || {}).value || ''; }\n      else if (posEl) { cfg.position = posEl.value; }\n      else { cfg.position = 'top'; }\n    }\n    if (action === 'js') { cfg.code = (panelShadow.getElementById('cfg-code') || {}).value || ''; if (!cfg.code) return; }\n    var lbl = (panelShadow.getElementById('label-input') || {}).value || '';\n    if (editing) {\n      var idx = shortcuts.findIndex(function(s) { return s.id === editing; });\n      if (idx !== -1) {\n        shortcuts[idx].shortcut = recordedCombo;\n        shortcuts[idx].action = action;\n        shortcuts[idx].config = cfg;\n        shortcuts[idx].label = lbl;\n      }\n    } else {\n      shortcuts.push({ id: genId(), shortcut: recordedCombo, action: action, config: cfg, label: lbl, createdAt: new Date().toISOString() });\n    }\n    save();\n    editing = null; recording = false;\n    renderList();\n  };\n\n  // Wire delete in form\n  var formDel = panelShadow.getElementById('form-del');\n  if (formDel) formDel.onclick = function() {\n    shortcuts = shortcuts.filter(function(s) { return s.id !== editing; });\n    save(); editing = null; renderList();\n  };\n}\n\nfunction panelCSS() {\n  return '* {box-sizing:border-box;margin:0;padding:0} ' +\n    '.panel {width:360px;max-height:60vh;overflow:hidden;display:flex;flex-direction:column;background:#161b22;border:1px solid #30363d;border-radius:12px;font:13px/1.5 -apple-system,BlinkMacSystemFont,\"Segoe UI\",Roboto,sans-serif;color:#c9d1d9;box-shadow:0 8px 32px rgba(0,0,0,.4)} ' +\n    '.hdr {display:flex;align-items:center;gap:8px;padding:10px 14px;border-bottom:1px solid #21262d} ' +\n    '.title {font-weight:700;font-size:13px;color:#e6edf3} .sub {font-size:11px;color:#8b949e;margin-left:auto} ' +\n    '.x {background:none;border:none;color:#8b949e;font-size:14px;cursor:pointer;padding:2px 6px;line-height:1;margin-left:4px;font-weight:600} .x:hover {color:#e6edf3} ' +\n    '.body {padding:12px 14px;overflow-y:auto;max-height:calc(60vh - 44px)} ' +\n    '.btn {padding:6px 12px;border-radius:6px;border:1px solid #30363d;background:#21262d;color:#c9d1d9;font:inherit;font-size:12px;font-weight:600;cursor:pointer} .btn:hover {background:#30363d} ' +\n    '.bp {background:#238636;border-color:#238636;color:#fff;width:100%;margin-bottom:10px} .bp:hover {background:#2ea043} ' +\n    '.bd {background:rgba(248,81,73,.1);border-color:#da3633;color:#f85149} .bd:hover {background:rgba(248,81,73,.2)} ' +\n    '.bs {padding:3px 8px;font-size:11px} ' +\n    '.list {display:flex;flex-direction:column;gap:4px} ' +\n    '.item {display:flex;align-items:center;gap:8px;padding:6px 8px;background:#0d1117;border:1px solid #21262d;border-radius:6px} ' +\n    '.item-dim {opacity:0.6} ' +\n    '.info {display:flex;flex-direction:column;gap:2px;overflow:hidden;flex:1} ' +\n    '.lbl {font-size:12px;color:#c9d1d9;overflow:hidden;text-overflow:ellipsis;white-space:nowrap} ' +\n    '.tag {font-size:9px;color:#8b949e;text-transform:uppercase;letter-spacing:0.5px} ' +\n    'code {font-size:11px;color:#79c0ff;background:rgba(56,139,253,.1);padding:1px 5px;border-radius:4px;white-space:nowrap;flex-shrink:0} ' +\n    '.empty {text-align:center;padding:12px;color:#484f58;font-size:12px} ' +\n    '.section-label {font-size:10px;font-weight:600;color:#8b949e;text-transform:uppercase;letter-spacing:0.5px;margin-bottom:6px} ' +\n    '.fl {display:block;font-size:11px;color:#8b949e;margin-bottom:4px;margin-top:8px} ' +\n    '.fl:first-child {margin-top:0} ' +\n    '.fi {width:100%;padding:6px 8px;border-radius:6px;border:1px solid #30363d;background:#0d1117;color:#c9d1d9;font:inherit;font-size:12px} ' +\n    '.fi:focus {outline:none;border-color:#58a6ff;box-shadow:0 0 0 3px rgba(56,139,253,.15)} ' +\n    '.ta {resize:vertical;min-height:48px;font-family:Consolas,\"Fira Code\",monospace;font-size:11px} ' +\n    '.rec {padding:8px 10px;border-radius:6px;border:2px dashed #30363d;background:#0d1117;cursor:pointer;text-align:center;min-height:36px;display:flex;align-items:center;justify-content:center} ' +\n    '.rec:focus {border-color:#58a6ff;outline:none} ' +\n    '.placeholder {color:#484f58;font-size:12px} ' +\n    '.err {color:#f85149;font-size:11px;margin-top:4px;min-height:16px} ' +\n    '.radios {display:flex;flex-direction:column;gap:4px} ' +\n    '.rl {font-size:12px;color:#c9d1d9;cursor:pointer;display:flex;align-items:center;gap:6px;padding:2px 0} ' +\n    '.rl input {accent-color:#58a6ff} ' +\n    '.row {display:flex;gap:6px;align-items:center} ' +\n    'select {padding:6px 8px;border-radius:6px;border:1px solid #30363d;background:#0d1117;color:#c9d1d9;font:inherit;font-size:12px}';\n}\n\n// ── Init ──\napi.addEventListener(window, 'message', function(e) {\n  if (!e.data || !e.data.__domo) return;\n  if (e.data.type === 'domo:command' && e.data.command === 'toggle-shortcuts-panel') {\n    if (panelOpen) closePanel(); else openPanel();\n  }\n  if (e.data.type === 'domo:openPanel' && e.data.pluginId === api.pluginId) {\n    if (panelOpen) closePanel(); else openPanel();\n  }\n});\n\napi.onCleanup(function() {\n  closePanel();\n});"
  }
}
